advanced_collections/__init__.py
advanced_collections/abc.py
advanced_collections/_src/__init__.py
advanced_collections/_src/big_dict.py
advanced_collections/_src/big_list.py
advanced_collections/_src/comparable.py
advanced_collections/_src/key_comparable.py
advanced_collections/_src/mutable_sequence_islice.py
advanced_collections/_src/mutable_sequence_islice_proxy.py
advanced_collections/_src/sequence_islice.py
advanced_collections/_src/sequence_islice_proxy.py
advanced_collections/_src/supports_length_hint.py
advanced_collections/_src/viewable_mutable_sequence.py
advanced_collections/_src/viewable_sequence.py
advanced_collections/queue/__init__.py
advanced_collections/queue/_src/__init__.py
advanced_collections/queue/_src/abc_queue.py
advanced_collections/queue/_src/deque.py
advanced_collections/queue/_src/fifo.py
advanced_collections/queue/_src/lifo.py
advanced_collections/queue/_src/max_queue.py
advanced_collections/queue/_src/min_queue.py
advanced_collections/queue/_src/queue_protocol.py
advanced_collections-1.0.0.dist-info/LICENSE
advanced_collections-1.0.0.dist-info/METADATA
advanced_collections-1.0.0.dist-info/WHEEL
advanced_collections-1.0.0.dist-info/top_level.txt
advanced_collections-1.0.0.dist-info/RECORD
